code128/format.py
code128/image.py
code128/svg.py
code128/__init__.py
code128/__main__.py
code128/tool/console.py
code128/tool/gui.py
code128/tool/ModifiedMixin.py
code128/tool/__init__.py
code128-0.3.dist-info/DESCRIPTION.rst
code128-0.3.dist-info/entry_points.txt
code128-0.3.dist-info/METADATA
code128-0.3.dist-info/metadata.json
code128-0.3.dist-info/RECORD
code128-0.3.dist-info/top_level.txt
code128-0.3.dist-info/WHEEL
