Metadata-Version: 1.1
Name: code128
Version: 0.3
Summary: Create code128 barcodes
Home-page: https://bitbucket.org/01100101/code128
Author: Felix Knopf
Author-email: felix.knopf@arcor.de
License: LGPLv2+
Keywords: barcode
Platform: UNKNOWN
Classifier: Development Status :: 4 - Beta
Classifier: Environment :: Console
Classifier: License :: OSI Approved :: GNU Lesser General Public License v2 or later (LGPLv2+)
Classifier: Operating System :: OS Independent
Classifier: Programming Language :: Python :: 3
Classifier: Topic :: Utilities
